odoo/addons/ssi_partner_identification/README.rst
odoo/addons/ssi_partner_identification/__init__.py
odoo/addons/ssi_partner_identification/__manifest__.py
odoo/addons/ssi_partner_identification/menu.xml
odoo/addons/ssi_partner_identification/security/ir.model.access.csv
odoo/addons/ssi_partner_identification/security/res_group_data.xml
odoo/addons/ssi_partner_identification/static/description/icon.png
odoo/addons/ssi_partner_identification/views/res_partner_id_category_view.xml
odoo/addons/ssi_partner_identification/views/res_partner_id_number_view.xml
odoo14_addon_ssi_partner_identification-14.0.1.1.2.dev2.dist-info/METADATA
odoo14_addon_ssi_partner_identification-14.0.1.1.2.dev2.dist-info/WHEEL
odoo14_addon_ssi_partner_identification-14.0.1.1.2.dev2.dist-info/top_level.txt
odoo14_addon_ssi_partner_identification-14.0.1.1.2.dev2.dist-info/RECORD
