Metadata-Version: 2.1
Name: odoo14-addon-ssi-partner-identification
Version: 14.0.1.1.2.dev2
Summary: Partner Identification
Home-page: https://simetri-sinergi.id
Author: OpenSynergy Indonesia, PT. Simetri Sinergi Indonesia
License: AGPL-3
Platform: UNKNOWN
Classifier: Programming Language :: Python
Classifier: Framework :: Odoo
Classifier: Framework :: Odoo :: 14.0
Classifier: License :: OSI Approved :: GNU Affero General Public License v3
Requires-Python: >=3.6
Requires-Dist: odoo14-addon-partner-identification
Requires-Dist: odoo14-addon-ssi-partner
Requires-Dist: odoo <14.1dev,>=14.0a
